gerritlib/__init__.py
gerritlib/gerrit.py
gerritlib/version.py
gerritlib/tests/__init__.py
gerritlib/tests/base.py
gerritlib/tests/test_gerritlib.py
gerritlib-0.11.0.dist-info/AUTHORS
gerritlib-0.11.0.dist-info/LICENSE
gerritlib-0.11.0.dist-info/METADATA
gerritlib-0.11.0.dist-info/WHEEL
gerritlib-0.11.0.dist-info/pbr.json
gerritlib-0.11.0.dist-info/top_level.txt
gerritlib-0.11.0.dist-info/RECORD
