Metadata-Version: 2.1
Name: gerritlib
Version: 0.11.0
Summary: Client library for accessing Gerrit.
Home-page: https://opendev.org/opendev/gerritlib
Author: OpenDev Team
Author-email: service-discuss@lists.opendev.org
Maintainer: OpenDev Team
Maintainer-email: service-discuss@lists.opendev.org
License: apache
Platform: UNKNOWN
Classifier: Topic :: Utilities
Classifier: Intended Audience :: Developers
Classifier: Intended Audience :: Information Technology
Classifier: Intended Audience :: System Administrators
Classifier: Environment :: Console
Classifier: License :: OSI Approved :: Apache Software License
Classifier: Operating System :: POSIX :: Linux
Classifier: Programming Language :: Python
Classifier: Programming Language :: Python :: 3
Classifier: Programming Language :: Python :: 3.10
Classifier: Programming Language :: Python :: 3.11
Classifier: Programming Language :: Python :: 3.12
Requires-Python: >= 3.10
Requires-Dist: paramiko (>=2.0.0)
Requires-Dist: pbr (>=0.11)
